clean_dotenv/__init__.py
clean_dotenv/__main__.py
clean_dotenv/_main.py
clean_dotenv/_parser.py
clean_dotenv-0.0.7.dist-info/LICENSE
clean_dotenv-0.0.7.dist-info/METADATA
clean_dotenv-0.0.7.dist-info/WHEEL
clean_dotenv-0.0.7.dist-info/entry_points.txt
clean_dotenv-0.0.7.dist-info/top_level.txt
clean_dotenv-0.0.7.dist-info/RECORD
